thetextdata/__init__.py
thetextdata/textdata.py
thetextdata-0.0.8.dist-info/LICENSE
thetextdata-0.0.8.dist-info/WHEEL
thetextdata-0.0.8.dist-info/METADATA
thetextdata-0.0.8.dist-info/RECORD
