Metadata-Version: 2.1
Name: thetextdata
Version: 0.0.8
Summary: Let's process some text
Home-page: https://github.com/bgokden/text-data
Author: Berk Gokden
Author-email: berkgokden@gmail.com
Requires-Python: >=3.7
Classifier: License :: OSI Approved :: Apache Software License
Classifier: Programming Language :: Python :: 3
Requires-Dist: spacy>=3.0.5
Requires-Dist: spacy_universal_sentence_encoder>=0.4.1
Requires-Dist: veriservice>=0.0.34
Requires-Dist: pandas>=1.1.2
Requires-Dist: tensorflow_text>=2.4.0
Requires-Dist: scikit-learn>=0.24.1
